{
	"meta": {
		"title": "小P的创意工坊",
		"description": "",
		"username": "P·junior"
	},
	"theme": {
		"colorBrand": "#de4331",
		"colorPrimary": "#4E3F42",
		"colorSecondary": "#7b888e",
		"colorBrandSecondary": "#FCC841",
		"colorBg": "#eeeeee",
		"colorBorder": "#ffffff",
		"colorCard": "#ffffff66",
		"colorArticle": "#ffffffcc"
	},
	"backgroundColors": [
		"#FCC841",
		"#DFEFFC",
		"#DEDE92",
		"#DE4331",
		"#FE9750",
		"#FCC841"
	],
	"artImages": [],
	"currentArtImageId": "",
	"backgroundImages": [
		{
			"id": "",
			"url": ""
		}
	],
	"currentBackgroundImageId": "",
	"socialButtons": [],
	"clockShowSeconds": false,
	"summaryInContent": false,
	"isCachePem": false,
	"hideEditButton": false,
	"enableCategories": true,
	"currentHatIndex": 3,
	"hatFlipped": false,
	"enableChristmas": false,
	"beian": {
		"text": "美ICP备000001号",
		"link": "https://www.wh.gov"
	}
}